tt_perf_report/__init__.py
tt_perf_report/perf_report.py
tt_perf_report-1.2.1.dist-info/licenses/LICENSE
tt_perf_report-1.2.1.dist-info/licenses/LICENSE_understanding.txt
tt_perf_report-1.2.1.dist-info/METADATA
tt_perf_report-1.2.1.dist-info/WHEEL
tt_perf_report-1.2.1.dist-info/entry_points.txt
tt_perf_report-1.2.1.dist-info/top_level.txt
tt_perf_report-1.2.1.dist-info/RECORD
