Metadata-Version: 2.4
Name: tt-perf-report
Version: 1.2.1
Summary: This tool analyzes performance traces from TT-Metal operations, providing insights into throughput, bottlenecks, and optimization opportunities.
License:                                  Apache License
Project-URL: Repository, https://github.com/tenstorrent/tt-perf-report
Keywords: tenstorrent,tt-metal
License-File: LICENSE
License-File: LICENSE_understanding.txt
Requires-Dist: pandas
Requires-Dist: matplotlib
Provides-Extra: test
Requires-Dist: pytest; extra == "test"
Requires-Dist: pytest-mock; extra == "test"
Dynamic: license-file
